tessfov/__init__.py
tessfov/data/tess_params.csv
tessfov/tessfov.py
tessfov-0.1.2.dist-info/LICENSE
tessfov-0.1.2.dist-info/WHEEL
tessfov-0.1.2.dist-info/METADATA
tessfov-0.1.2.dist-info/RECORD
