Metadata-Version: 2.1
Name: tessfov
Version: 0.1.2
Summary: 
Author: Christina Hedges
Author-email: christina.l.hedges@nasa.gov
Requires-Python: >=3.8,<4.0
Classifier: Programming Language :: Python :: 3
Classifier: Programming Language :: Python :: 3.8
Classifier: Programming Language :: Python :: 3.9
Requires-Dist: matplotlib (>=3.5.2,<4.0.0)
Requires-Dist: numpy (>=1.22.3,<2.0.0)
Requires-Dist: pandas (>=1.4.2,<2.0.0)
Requires-Dist: tess-point (>=0.7.1,<0.8.0)
